{"chunk_definitions":[{"row":7,"row_count":1,"visible":true,"expansion_state":0,"options":{"engine":"r","label":"unnamed-chunk-2"},"document_id":"0F17FF5D","chunk_id":"cv59ecj6bmi0e","chunk_label":"unnamed-chunk-1"},{"row":16,"row_count":1,"visible":true,"expansion_state":0,"options":{"engine":"r","label":"unnamed-chunk-3"},"document_id":"0F17FF5D","chunk_id":"ct21limmnprch","chunk_label":"unnamed-chunk-2"},{"row":22,"row_count":1,"visible":true,"expansion_state":0,"options":{"engine":"r","label":"unnamed-chunk-4"},"document_id":"0F17FF5D","chunk_id":"crgkgv29odi11","chunk_label":"unnamed-chunk-3"},{"row":31,"row_count":1,"visible":true,"expansion_state":0,"options":{"engine":"r","label":"unnamed-chunk-5"},"document_id":"0F17FF5D","chunk_id":"crhajdevhpxrp","chunk_label":"unnamed-chunk-4"},{"row":36,"row_count":1,"visible":true,"expansion_state":0,"options":{"engine":"r","label":"unnamed-chunk-6"},"document_id":"0F17FF5D","chunk_id":"cv7fpvno41c1q","chunk_label":"unnamed-chunk-5"}],"doc_write_time":1646088563}