{"chunk_definitions":[{"row":9,"row_count":1,"visible":true,"expansion_state":0,"options":{"engine":"r","label":"unnamed-chunk-2"},"document_id":"D55B5554","chunk_id":"cwnjz07ybpkzd","chunk_label":"unnamed-chunk-1"},{"row":17,"row_count":1,"visible":true,"expansion_state":0,"options":{"engine":"r","label":"unnamed-chunk-97"},"document_id":"D55B5554","chunk_id":"c111gh5xpjirq","chunk_label":"unnamed-chunk-2"},{"row":26,"row_count":1,"visible":true,"expansion_state":0,"options":{"engine":"r","label":"unnamed-chunk-98"},"document_id":"D55B5554","chunk_id":"ccvssifp06l7u","chunk_label":"unnamed-chunk-3"},{"row":31,"row_count":1,"visible":true,"expansion_state":0,"options":{"engine":"r","label":"unnamed-chunk-99"},"document_id":"D55B5554","chunk_id":"cqf7wnknqegxn","chunk_label":"unnamed-chunk-4"},{"row":35,"row_count":1,"visible":true,"expansion_state":0,"options":{"engine":"sql","connection":"con","label":"unnamed-chunk-100"},"document_id":"D55B5554","chunk_id":"cb2liwyy4yk4q","chunk_label":"unnamed-chunk-5"},{"row":39,"row_count":1,"visible":true,"expansion_state":0,"options":{"engine":"sql","connection":"con","label":"unnamed-chunk-101"},"document_id":"D55B5554","chunk_id":"c57rf5lzy6aex","chunk_label":"unnamed-chunk-6"},{"row":43,"row_count":1,"visible":true,"expansion_state":0,"options":{"engine":"sql","connection":"con","label":"unnamed-chunk-102"},"document_id":"D55B5554","chunk_id":"c1xl4wcdy6di1","chunk_label":"unnamed-chunk-7"},{"row":52,"row_count":1,"visible":true,"expansion_state":0,"options":{"engine":"sql","connection":"con","label":"unnamed-chunk-103"},"document_id":"D55B5554","chunk_id":"cbxf7y1ow104n","chunk_label":"unnamed-chunk-8"},{"row":60,"row_count":1,"visible":true,"expansion_state":0,"options":{"engine":"sql","connection":"con","label":"unnamed-chunk-104"},"document_id":"D55B5554","chunk_id":"c55yv5uigr0xv","chunk_label":"unnamed-chunk-9"},{"row":75,"row_count":1,"visible":true,"expansion_state":0,"options":{"engine":"sql","connection":"con","label":"unnamed-chunk-105"},"document_id":"D55B5554","chunk_id":"c4pmnmu292pej","chunk_label":"unnamed-chunk-10"},{"row":80,"row_count":1,"visible":true,"expansion_state":0,"options":{"engine":"r","label":"unnamed-chunk-106"},"document_id":"D55B5554","chunk_id":"c3dxki6d7o601","chunk_label":"unnamed-chunk-11"},{"row":94,"row_count":1,"visible":true,"expansion_state":0,"options":{"engine":"r","label":"unnamed-chunk-107"},"document_id":"D55B5554","chunk_id":"cxzqlb6bghnxm","chunk_label":"unnamed-chunk-12"},{"row":98,"row_count":1,"visible":true,"expansion_state":0,"options":{"engine":"r","label":"unnamed-chunk-108"},"document_id":"D55B5554","chunk_id":"cpzrwuh1cby4m","chunk_label":"unnamed-chunk-13"},{"row":102,"row_count":1,"visible":true,"expansion_state":0,"options":{"engine":"r","label":"unnamed-chunk-109"},"document_id":"D55B5554","chunk_id":"c5qq37vlwqffl","chunk_label":"unnamed-chunk-14"},{"row":106,"row_count":1,"visible":true,"expansion_state":0,"options":{"engine":"r","label":"unnamed-chunk-110"},"document_id":"D55B5554","chunk_id":"cjoffjird3hem","chunk_label":"unnamed-chunk-15"},{"row":110,"row_count":1,"visible":true,"expansion_state":0,"options":{"engine":"r","label":"unnamed-chunk-111"},"document_id":"D55B5554","chunk_id":"cugrevp62fk9i","chunk_label":"unnamed-chunk-16"},{"row":114,"row_count":1,"visible":true,"expansion_state":0,"options":{"engine":"r","label":"unnamed-chunk-112"},"document_id":"D55B5554","chunk_id":"cmn06n0p4rfvs","chunk_label":"unnamed-chunk-17"},{"row":119,"row_count":1,"visible":true,"expansion_state":0,"options":{"engine":"r","label":"unnamed-chunk-113"},"document_id":"D55B5554","chunk_id":"cry89gu4be65t","chunk_label":"unnamed-chunk-18"},{"row":123,"row_count":1,"visible":true,"expansion_state":0,"options":{"engine":"r","label":"unnamed-chunk-115"},"document_id":"D55B5554","chunk_id":"cxrwmlbmy0vck","chunk_label":"unnamed-chunk-19"},{"row":127,"row_count":1,"visible":true,"expansion_state":0,"options":{"engine":"r","label":"unnamed-chunk-116"},"document_id":"D55B5554","chunk_id":"cyg97g7qkigx6","chunk_label":"unnamed-chunk-20"},{"row":131,"row_count":1,"visible":true,"expansion_state":0,"options":{"engine":"r","label":"unnamed-chunk-117"},"document_id":"D55B5554","chunk_id":"cubg7fmcwfome","chunk_label":"unnamed-chunk-21"},{"row":152,"row_count":1,"visible":true,"expansion_state":0,"options":{"engine":"r","label":"unnamed-chunk-2"},"document_id":"D55B5554","chunk_id":"cvt9jwsqh8frs","chunk_label":"unnamed-chunk-24"},{"row":156,"row_count":1,"visible":true,"expansion_state":0,"options":{"engine":"sql","connection":"con","label":"unnamed-chunk-20"},"document_id":"D55B5554","chunk_id":"css2p6daesadj","chunk_label":"unnamed-chunk-25"},{"row":161,"row_count":1,"visible":true,"expansion_state":0,"options":{"engine":"sql","connection":"con","label":"unnamed-chunk-4"},"document_id":"D55B5554","chunk_id":"c1cgx1th0ivfb","chunk_label":"unnamed-chunk-26"},{"row":165,"row_count":1,"visible":true,"expansion_state":0,"options":{"engine":"sql","connection":"con","label":"unnamed-chunk-5"},"document_id":"D55B5554","chunk_id":"c40yv4tide5sd","chunk_label":"unnamed-chunk-27"},{"row":169,"row_count":1,"visible":true,"expansion_state":0,"options":{"engine":"sql","connection":"con","label":"unnamed-chunk-6"},"document_id":"D55B5554","chunk_id":"ckl4ileugfswr","chunk_label":"unnamed-chunk-28"},{"row":175,"row_count":1,"visible":true,"expansion_state":0,"options":{"engine":"sql","connection":"con","label":"unnamed-chunk-18"},"document_id":"D55B5554","chunk_id":"caxc1m0bndfll","chunk_label":"unnamed-chunk-29"},{"row":179,"row_count":1,"visible":true,"expansion_state":0,"options":{"engine":"sql","connection":"con","label":"unnamed-chunk-21"},"document_id":"D55B5554","chunk_id":"cnh7a9ig7ulk2","chunk_label":"unnamed-chunk-30"},{"row":183,"row_count":1,"visible":true,"expansion_state":0,"options":{"engine":"r","label":"unnamed-chunk-22"},"document_id":"D55B5554","chunk_id":"cu8unianq4paa","chunk_label":"unnamed-chunk-31"}],"doc_write_time":1646409986}